txtmarker/__init__.py
txtmarker/base.py
txtmarker/factory.py
txtmarker/pdf.py
txtmarker-1.1.0.dist-info/LICENSE
txtmarker-1.1.0.dist-info/METADATA
txtmarker-1.1.0.dist-info/WHEEL
txtmarker-1.1.0.dist-info/top_level.txt
txtmarker-1.1.0.dist-info/RECORD
