Metadata-Version: 2.1
Name: txtmarker
Version: 1.1.0
Summary: Finds and highlights text in documents
Home-page: https://github.com/neuml/txtmarker
Author: NeuML
License: Apache 2.0: http://www.apache.org/licenses/LICENSE-2.0
Project-URL: Documentation, https://github.com/neuml/txtmarker
Project-URL: Issue Tracker, https://github.com/neuml/txtmarker/issues
Project-URL: Source Code, https://github.com/neuml/txtmarker
Keywords: pdf highlight text search
Classifier: License :: OSI Approved :: Apache Software License
Classifier: Operating System :: OS Independent
Classifier: Programming Language :: Python :: 3
Classifier: Topic :: Software Development
Classifier: Topic :: Utilities
Requires-Python: >=3.9
License-File: LICENSE
Requires-Dist: pdfminer.six (>=20201018)
Requires-Dist: pdf-annotate (>=0.11.0)
